{
  "title": "Project",
  "description": "Configuration for the package.",
  "type": "object",
  "properties": {
    "base": {
      "title": "Base",
      "description": "The base directory for the project data.",
      "format": "directory-path",
      "type": "string"
    },
    "trials": {
      "title": "Trials",
      "description": "The directory in which the individual trials are. Must be relative to the base directory.",
      "format": "directory-path",
      "type": "string"
    },
    "results": {
      "title": "Results",
      "description": "The directory in which the results will go. Must be relative to the base directory. Will be created if it is missing.",
      "format": "directory-path",
      "type": "string"
    },
    "results_file": {
      "title": "Results File",
      "description": "The name of the results file. Will go in the results directory. Default: results.csv",
      "default": "results.csv",
      "type": "string",
      "format": "path"
    },
    "directory_per_trial": {
      "title": "Directory Per Trial",
      "description": "The directory in which the data are for a given trial. Must be relative to a trial folder, and all trials must share this pattern.",
      "type": "string",
      "format": "path"
    },
    "fit": {
      "$ref": "#/definitions/Fit"
    }
  },
  "required": [
    "base",
    "trials",
    "results",
    "directory_per_trial",
    "fit"
  ],
  "additionalProperties": false,
  "definitions": {
    "Fit": {
      "title": "Fit",
      "description": "Configure the linear regression of thermocouple temperatures vs. position.",
      "type": "object",
      "properties": {
        "thermocouple_pos": {
          "title": "Thermocouple Pos",
          "description": "Thermocouple positions.",
          "type": "array",
          "items": {
            "type": "number"
          }
        },
        "do_plot": {
          "title": "Do Plot",
          "description": "Whether to plot the linear regression.",
          "default": false,
          "type": "boolean"
        }
      },
      "required": [
        "thermocouple_pos"
      ]
    }
  }
}
